README.txt
setup.py
hangul/__init__.py
hangul/translit.py
hangul.translit.egg-info/PKG-INFO
hangul.translit.egg-info/SOURCES.txt
hangul.translit.egg-info/dependency_links.txt
hangul.translit.egg-info/namespace_packages.txt
hangul.translit.egg-info/top_level.txt