Metadata-Version: 1.0
Name: hangul.translit
Version: 0.1
Summary: Transliteration of Hangul(Korean) to Roman writing system following Revised Romanization of Korean(2000).
Home-page: UNKNOWN
Author: Lee Sun-yeon
Author-email: lee.soonyeon@gmail.com
License: BSD
Keywords: korean hangul romanization transliteration
Platform: UNKNOWN
Classifier: Programming Language :: Python
Classifier: Topic :: Software Development :: Libraries :: Python Modules
